rayspatial/__init__.py
rayspatial/engine/__init__.py
rayspatial/engine/client/__init__.py
rayspatial/engine/client/interactive_session.py
rayspatial/engine/function_helper.py
rayspatial/engine/function_node.py
rayspatial/engine/gve_object/ai.py
rayspatial/engine/gve_object/feature.py
rayspatial/engine/gve_object/geometry.py
rayspatial/engine/gve_object/image.py
rayspatial/engine/map/__init__.py
rayspatial/engine/map/gve_layer.py
rayspatial/engine/map/gve_map.py
rayspatial/engine/serialize/__init__.py
rayspatial/engine/serialize/serializer.py
rayspatial/engine/utils/__init__.py
rayspatial/engine/utils/utils.py
rayspatial/serve/__init__.py
rayspatial/serve/common/__init__.py
rayspatial/serve/common/constants.py
rayspatial/serve/common/obj/__init__.py
rayspatial/serve/common/obj/datasource.py
rayspatial/serve/common/obj/execute.py
rayspatial/serve/common/obj/image.py
rayspatial/serve/common/obj/imageCollection.py
rayspatial/serve/common/obj/requestHeader.py
rayspatial/serve/common/obj/rsResponse.py
rayspatial/serve/common/route.py
rayspatial/serve/config/__init__.py
rayspatial/serve/config/config.ini
rayspatial/serve/config/config.py
rayspatial/serve/core/actor/__init__.py
rayspatial/serve/core/actor/baseCore.py
rayspatial/serve/core/actor/coreActor.py
rayspatial/serve/core/dataframe/__init__.py
rayspatial/serve/core/dataframe/imageDataFrame.py
rayspatial/serve/core/datasource/datasourceBase.py
rayspatial/serve/core/error/__init__.py
rayspatial/serve/core/error/gve_error.py
rayspatial/serve/core/image/__init__.py
rayspatial/serve/core/image/imageBase.py
rayspatial/serve/core/image/imageOperate.py
rayspatial/serve/core/imageCollection/imageCollectionBase.py
rayspatial/serve/core/imageCollection/imageCollectionOptions.py
rayspatial/serve/core/utils/__init__.py
rayspatial/serve/core/utils/fileUtils.py
rayspatial/serve/core/utils/imageReadUtils.py
rayspatial/serve/core/utils/imageUtils.py
rayspatial/serve/core/utils/imageWriteUtils.py
rayspatial-0.0.24.dist-info/LICENSE
rayspatial-0.0.24.dist-info/METADATA
rayspatial-0.0.24.dist-info/WHEEL
rayspatial-0.0.24.dist-info/RECORD
