Metadata-Version: 2.3
Name: rayspatial
Version: 0.0.24
Summary: A Python package for distributed spatial data processing based on Ray
License: MIT
Keywords: ray,spatial,distributed,gis,remote sensing
Author: rsDev-zh
Author-email: 1924605670@qq.com
Requires-Python: >=3.10
Classifier: License :: OSI Approved :: MIT License
Classifier: Programming Language :: Python :: 3
Classifier: Programming Language :: Python :: 3.10
Classifier: Programming Language :: Python :: 3.11
Classifier: Programming Language :: Python :: 3.12
Classifier: Programming Language :: Python :: 3.13
Requires-Dist: fastapi
Requires-Dist: geopandas
Requires-Dist: ipyleaflet
Requires-Dist: planetary-computer
Requires-Dist: pyarrow
Requires-Dist: pydantic
Requires-Dist: pyproj (==3.6.1)
Requires-Dist: rasterio
Requires-Dist: ray[client,serve] (==2.43.0)
Requires-Dist: requests
Requires-Dist: tqdm
Requires-Dist: urllib3
